keras_mobile/__init__.py
keras_mobile/blocks/__init__.py
keras_mobile/blocks/conv.py
keras_mobile/blocks/normalization.py
keras_mobile/functions/__init__.py
keras_mobile/functions/activations.py
keras_mobile/layers/__init__.py
keras_mobile/layers/activations.py
keras_mobile/layers/normalization.py
keras_mobile-1.0.2.dist-info/METADATA
keras_mobile-1.0.2.dist-info/RECORD
keras_mobile-1.0.2.dist-info/WHEEL
keras_mobile-1.0.2.dist-info/top_level.txt
